pyevio/__init__.py
pyevio/__main__.py
pyevio/bank.py
pyevio/buffer_reader.py
pyevio/cli.py
pyevio/display.py
pyevio/event.py
pyevio/evio_file.py
pyevio/file_header.py
pyevio/record.py
pyevio/record_header.py
pyevio/roc_time_slice_bank.py
pyevio/utils.py
pyevio/cli/__init__.py
pyevio/cli/ana.py
pyevio/cli/debug.py
pyevio/cli/dump.py
pyevio/cli/event.py
pyevio/cli/hex.py
pyevio/cli/info.py
pyevio/cli/record.py
pyevio/cli/ui.py
pyevio/ui/__init__.py
pyevio/ui/app.py
pyevio-0.2.0.dist-info/METADATA
pyevio-0.2.0.dist-info/WHEEL
pyevio-0.2.0.dist-info/entry_points.txt
pyevio-0.2.0.dist-info/top_level.txt
pyevio-0.2.0.dist-info/RECORD
